{"name":"User registration whit validations","id":"as-an-inlaze-user-i-want-to-register-my-account-on-the-platform;user-registration-whit-validations","testSteps":[{"number":1,"description":"Example: {full_name\u003d\"Register Test\", email\u003dregisterTest@gmail.com, password\u003dColombia2024.}","duration":19455,"startTime":"2024-12-18T23:38:01.053288400-05:00[America/Bogota]","exception":{"errorType":"java.lang.AssertionError","message":"The system is accepting the wrong format in the email field expected:\u003ctrue\u003e but was:\u003cnull\u003e","stackTrace":[{"classLoaderName":"app","declaringClass":"steps.login.SingUpSteps","methodName":"validateEmail","fileName":"SingUpSteps.java","lineNumber":40,"format":1},{"classLoaderName":"app","declaringClass":"steps.login.SingUpSteps","methodName":"validateFields","fileName":"SingUpSteps.java","lineNumber":21,"format":1},{"classLoaderName":"app","declaringClass":"defintions.login.SignUpDefinitions","methodName":"completeTheRegistrationFormWhitValidations","fileName":"SignUpDefinitions.java","lineNumber":18,"format":1},{"declaringClass":"✽","methodName":"complete the registration form whit validations \"Register Test\" registerTest@gmail.com Colombia2024.","fileName":"src/test/resources/features/register_user.feature","lineNumber":18,"format":0}]},"result":"FAILURE","precondition":false,"level":0,"children":[{"number":2,"description":"Given that the user enters the registration module","duration":204,"startTime":"2024-12-18T23:38:03.368700600-05:00[America/Bogota]","result":"SUCCESS","precondition":false,"level":1},{"number":3,"description":"When complete the registration form whit validations \"Register Test\" registerTest@gmail.com Colombia2024.","duration":16584,"startTime":"2024-12-18T23:38:03.574769900-05:00[America/Bogota]","exception":{"errorType":"java.lang.AssertionError","message":"The system is accepting the wrong format in the email field expected:\u003ctrue\u003e but was:\u003cnull\u003e","stackTrace":[{"classLoaderName":"app","declaringClass":"steps.login.SingUpSteps","methodName":"validateEmail","fileName":"SingUpSteps.java","lineNumber":40,"format":1},{"classLoaderName":"app","declaringClass":"steps.login.SingUpSteps","methodName":"validateFields","fileName":"SingUpSteps.java","lineNumber":21,"format":1},{"classLoaderName":"app","declaringClass":"defintions.login.SignUpDefinitions","methodName":"completeTheRegistrationFormWhitValidations","fileName":"SignUpDefinitions.java","lineNumber":18,"format":1},{"declaringClass":"✽","methodName":"complete the registration form whit validations \"Register Test\" registerTest@gmail.com Colombia2024.","fileName":"src/test/resources/features/register_user.feature","lineNumber":18,"format":0}]},"result":"FAILURE","precondition":false,"level":1},{"number":4,"description":"Then You can view the confirmation of your account creation","duration":5,"startTime":"2024-12-18T23:38:20.161882-05:00[America/Bogota]","result":"SKIPPED","precondition":false,"level":1}]}],"userStory":{"id":"as-an-inlaze-user-i-want-to-register-my-account-on-the-platform","storyName":"As an Inlaze user I want to register my account on the platform","path":"src/test/resources/features/register_user.feature","type":"feature"},"featureTag":{"name":"Features/As an Inlaze user I want to register my account on the platform","type":"feature","displayName":"Features/As an Inlaze user I want to register my account on the platform"},"title":"User registration whit validations","tags":[{"name":"As an Inlaze user I want to register my account on the platform","type":"feature","displayName":"As an Inlaze user I want to register my account on the platform"},{"name":"validations_register","type":"tag","displayName":"validations_register"},{"name":"test","type":"tag","displayName":"test"}],"startTime":"2024-12-18T23:38:01.049208900-05:00[America/Bogota]","duration":19461,"testFailureCause":{"errorType":"java.lang.AssertionError","message":"The system is accepting the wrong format in the email field expected:\u003ctrue\u003e but was:\u003cnull\u003e","stackTrace":[{"classLoaderName":"app","declaringClass":"steps.login.SingUpSteps","methodName":"validateEmail","fileName":"SingUpSteps.java","lineNumber":40,"format":1},{"classLoaderName":"app","declaringClass":"steps.login.SingUpSteps","methodName":"validateFields","fileName":"SingUpSteps.java","lineNumber":21,"format":1},{"classLoaderName":"app","declaringClass":"defintions.login.SignUpDefinitions","methodName":"completeTheRegistrationFormWhitValidations","fileName":"SignUpDefinitions.java","lineNumber":18,"format":1},{"declaringClass":"✽","methodName":"complete the registration form whit validations \"Register Test\" registerTest@gmail.com Colombia2024.","fileName":"src/test/resources/features/register_user.feature","lineNumber":18,"format":0}]},"testFailureClassname":"java.lang.AssertionError","testFailureMessage":"The system is accepting the wrong format in the email field expected:\u003ctrue\u003e but was:\u003cnull\u003e","testFailureSummary":"FAILURE;java.lang.AssertionError;The system is accepting the wrong format in the email field expected:\u003ctrue\u003e but was:\u003cnull\u003e;SingUpSteps.java","projectKey":"","annotatedResult":"FAILURE","isManualTestingUpToDate":false,"dataTable":{"headers":["full_name","email","password"],"rows":[{"values":["\"Register Test\"","registerTest@gmail.com","Colombia2024."],"lineNumber":0,"result":"FAILURE"}],"predefinedRows":true,"scenarioOutline":"Given that the user enters the registration module\n\rWhen complete the registration form whit validations \u003cfull_name\u003e \u003cemail\u003e \u003cpassword\u003e\n\rThen You can view the confirmation of your account creation\n\r","dataSetDescriptors":[{"startRow":0,"rowCount":0,"name":""}]},"manual":false,"testSource":"Cucumber","result":"FAILURE","scenarioOutline":"Given that the user enters the registration module\r\nWhen complete the registration form whit validations \u003cfull_name\u003e \u003cemail\u003e \u003cpassword\u003e\r\nThen You can view the confirmation of your account creation"}